fragly/__init__.py
fragly/client.py
fragly/exceptions.py
fragly-0.1.2.dist-info/METADATA
fragly-0.1.2.dist-info/WHEEL
fragly-0.1.2.dist-info/top_level.txt
fragly-0.1.2.dist-info/RECORD
