Metadata-Version: 2.4
Name: fragly
Version: 0.1.2
Summary: Async Python client for your FraglyFragment API service
Author: Andrey
Classifier: Programming Language :: Python :: 3
Classifier: Operating System :: OS Independent
Classifier: Intended Audience :: Developers
Classifier: Topic :: Software Development :: Libraries
Requires-Python: >=3.9
Requires-Dist: aiohttp>=3.9.0
Dynamic: author
Dynamic: classifier
Dynamic: requires-dist
Dynamic: requires-python
Dynamic: summary
